{"name":"Looking up the definition of \u0027apple\u0027","id":"lookup-a-definition;looking-up-the-definition-of--apple-","testSteps":[{"number":1,"description":"Given the user is on the Wikionary home page","duration":11826,"startTime":"2018-06-26T11:09:58.636-05:00[America/Bogota]","screenshots":[{"screenshot":"34c871eb1bea57d1b67695609e95dc6538504735207dc64245e12ac9bd649a60.png"}],"result":"SUCCESS","precondition":false,"children":[{"number":2,"description":"Is the home page","duration":10219,"startTime":"2018-06-26T11:09:59.524-05:00[America/Bogota]","screenshots":[{"screenshot":"34c871eb1bea57d1b67695609e95dc6538504735207dc64245e12ac9bd649a60.png"}],"result":"SUCCESS","precondition":false}]},{"number":3,"description":"When the user looks up the definition of the word \u0027apple\u0027","duration":5775,"startTime":"2018-06-26T11:10:10.462-05:00[America/Bogota]","screenshots":[{"screenshot":"72e0353a39e3ac92ad01adab782c18430c5c1fe4ae5ceffbe1d928fd70692ff1.png"}],"result":"SUCCESS","precondition":false,"children":[{"number":4,"description":"Looks for: apple","duration":4942,"startTime":"2018-06-26T11:10:10.859-05:00[America/Bogota]","screenshots":[{"screenshot":"72e0353a39e3ac92ad01adab782c18430c5c1fe4ae5ceffbe1d928fd70692ff1.png"}],"result":"SUCCESS","precondition":false,"children":[{"number":5,"description":"Enters: apple","duration":1463,"startTime":"2018-06-26T11:10:11.245-05:00[America/Bogota]","screenshots":[{"screenshot":"fd86acea6ec5a8120b896ac28592a262a17cc7201843ab22367c9f8b5b625089.png"}],"result":"SUCCESS","precondition":false},{"number":6,"description":"Starts search","duration":2513,"startTime":"2018-06-26T11:10:12.709-05:00[America/Bogota]","screenshots":[{"screenshot":"adb01c0055e06426dffa784bf66d5ef8febf091b1effc50c18ce4a1267720739.png"},{"screenshot":"a39edf7aed3091c5427e2259886eaa80fdbc1c6fcf4fb899dda421bd02e50a5b.png"}],"result":"SUCCESS","precondition":false}]}]},{"number":7,"description":"Then they should see the definition \u0027A common, round fruit produced by the tree Malus domestica, cultivated in temperate climates.\u0027","duration":2840,"startTime":"2018-06-26T11:10:16.237-05:00[America/Bogota]","screenshots":[{"screenshot":"72e0353a39e3ac92ad01adab782c18430c5c1fe4ae5ceffbe1d928fd70692ff1.png"}],"result":"SUCCESS","precondition":false,"children":[{"number":8,"description":"Should see definition: A common, round fruit produced by the tree Malus domestica, cultivated in temperate climates.","duration":2013,"startTime":"2018-06-26T11:10:16.630-05:00[America/Bogota]","screenshots":[{"screenshot":"72e0353a39e3ac92ad01adab782c18430c5c1fe4ae5ceffbe1d928fd70692ff1.png"}],"result":"SUCCESS","precondition":false}]}],"userStory":{"id":"lookup-a-definition","storyName":"Lookup a definition","path":"src/test/resources/features/consult_dictionary/LookupADefinition.feature","narrative":"  In order to talk better\n  As an English student\n  I want to look up word definitions","type":"feature"},"featureTag":{"name":"Consult dictionary/Lookup a definition","type":"feature"},"title":"Looking up the definition of \u0027apple\u0027","tags":[{"name":"Consult dictionary","type":"capability"},{"name":"Consult dictionary/Lookup a definition","type":"feature"}],"startTime":"2018-06-26T11:09:58.032-05:00[America/Bogota]","duration":21237,"projectKey":"","sessionId":"d5f667f0c67471e0d23247ba4f018dd9","driver":"chrome","manual":false,"testSource":"Cucumber","result":"SUCCESS"}